a4pdf-0.2.0.dist-info/METADATA
a4pdf-0.2.0.dist-info/WHEEL
a4pdf-0.2.0.dist-info/COPYING
.a4pdf.mesonpy.libs/fmt.dll
.a4pdf.mesonpy.libs/z.dll
.a4pdf.mesonpy.libs/png16-16.dll
.a4pdf.mesonpy.libs/lcms2-2.dll
.a4pdf.mesonpy.libs/jpeg-8.2.2.dll
.a4pdf.mesonpy.libs/freetype-6.dll
.a4pdf.mesonpy.libs/tiff4.dll
.a4pdf.mesonpy.libs/a4pdf.dll
a4pdf-0.2.0.data/scripts/linkicc.exe
a4pdf-0.2.0.data/scripts/psicc.exe
a4pdf-0.2.0.data/scripts/transicc.exe
a4pdf-0.2.0.data/purelib/a4pdf.py
a4pdf-0.2.0.dist-info/RECORD
