Metadata-Version: 2.1
Name: a4pdf
Version: 0.2.0
Summary: A color managed PDF generation library tech preview
Author-Email: Jussi Pakkanen <jpakkane@gmail.com>
License:                                  Apache License
Classifier: Development Status :: 2 - Pre-Alpha
Classifier: Operating System :: POSIX :: Linux
Classifier: Operating System :: Microsoft :: Windows
Classifier: Programming Language :: Python :: 3
Classifier: Programming Language :: C++
Classifier: Topic :: Software Development :: Libraries :: Python Modules
Requires-Python: >=3.8
